scripts/__init__.py
scripts/app.py
vuhx4_mysum-0.0.1.dist-info/licenses/license
vuhx4_mysum-0.0.1.dist-info/METADATA
vuhx4_mysum-0.0.1.dist-info/WHEEL
vuhx4_mysum-0.0.1.dist-info/top_level.txt
vuhx4_mysum-0.0.1.dist-info/RECORD
