Metadata-Version: 2.4
Name: vuhx4-mysum
Version: 0.0.1
Summary: Sort description
Home-page: https://github.com/pypa/sampleproject
Author: Xuan Vu
Author-email: xuanvuzzz2601@gmail.com
Classifier: Programming Language :: Python :: 2
Classifier: License :: OSI Approved :: MIT License
Classifier: Operating System :: OS Independent
License-File: license
Dynamic: author
Dynamic: author-email
Dynamic: classifier
Dynamic: description
Dynamic: description-content-type
Dynamic: home-page
Dynamic: license-file
Dynamic: summary
